pow_zodb/FileStorageZODB.py
pow_zodb/ZODB.py
pow_zodb/__init__.py
pow_store_zodb-0.1.1.dist-info/METADATA
pow_store_zodb-0.1.1.dist-info/WHEEL
pow_store_zodb-0.1.1.dist-info/entry_points.txt
pow_store_zodb-0.1.1.dist-info/top_level.txt
pow_store_zodb-0.1.1.dist-info/RECORD
