Metadata-Version: 2.1
Name: pow-store-zodb
Version: 0.1.1
Summary: rdflib extension adding ZODB as back-end store. Forked from rdflib-zodb
Home-page: http://github.com/openworm/rdflib-zodb
Author: Mark Watts
Author-email: mark@openworm.org
License: BSD
Platform: any
Classifier: Programming Language :: Python
Classifier: Programming Language :: Python :: 3
Classifier: Programming Language :: Python :: 3.6
Classifier: Programming Language :: Python :: 3.7
Classifier: Programming Language :: Python :: 3.8
Classifier: Programming Language :: Python :: 3.9
Classifier: License :: OSI Approved :: BSD License
Classifier: Topic :: Software Development :: Libraries :: Python Modules
Classifier: Operating System :: OS Independent
Classifier: Natural Language :: English
Requires-Dist: rdflib (>=4.1.0)
Requires-Dist: BTrees
Requires-Dist: transaction
Requires-Dist: ZODB
